bst_log_utils/gcs_log_utils.py
bst_log_utils/log_parse_db.py
bst_log_utils/log_to_cdf.py
bst_log_utils/log_utils.py
bst_log_utils/user_payloads/20240422_hurricane-app.xml
bst_log_utils/user_payloads/s0_data.xml
bst_log_utils-0.0.4.dist-info/licenses/LICENSE
bst_log_utils-0.0.4.dist-info/METADATA
bst_log_utils-0.0.4.dist-info/WHEEL
bst_log_utils-0.0.4.dist-info/top_level.txt
bst_log_utils-0.0.4.dist-info/RECORD
