Metadata-Version: 2.4
Name: bst_log_utils
Version: 0.0.4
Summary: Black Swift Technologies Log Parsing Tools
Author-email: Maciej Stachura <stachura@blackswifttech.com>, Jack Elston <elstonj@blackswifttech.com>
Project-URL: Homepage, https://bst/aero
Project-URL: Issues, https://bst.aero/support
Classifier: Programming Language :: Python :: 3
Classifier: Operating System :: POSIX
Requires-Python: >=3.8
License-File: LICENSE
Requires-Dist: bst_helper_functions==0.0.2
Requires-Dist: certifi==2025.1.31
Requires-Dist: cftime==1.6.4.post1
Requires-Dist: contourpy==1.3.1
Requires-Dist: cycler==0.12.1
Requires-Dist: fonttools==4.56.0
Requires-Dist: geomag==0.9.2015
Requires-Dist: h5py==3.13.0
Requires-Dist: kiwisolver==1.4.8
Requires-Dist: lxml==5.3.1
Requires-Dist: matplotlib==3.10.1
Requires-Dist: netCDF4==1.7.2
Requires-Dist: numpy==2.2.4
Requires-Dist: packaging==24.2
Requires-Dist: pillow==11.1.0
Requires-Dist: pyparsing==3.2.1
Requires-Dist: pyproj==3.7.1
Requires-Dist: python-dateutil==2.9.0.post0
Requires-Dist: pytz==2025.2
Requires-Dist: scipy==1.15.2
Requires-Dist: simplekml==1.3.6
Requires-Dist: six==1.17.0
Dynamic: license-file
